README.md
setup.py
tests/resources/__init__.py
tests/tezosetl/__init__.py
tests/tezosetl/helpers.py
tests/tezosetl/mock_tezos_rpc.py
tests/tezosetl/service/__init__.py
tests/tezosetl/service/test_tezos_block_range_service.py
tezos_etl.egg-info/PKG-INFO
tezos_etl.egg-info/SOURCES.txt
tezos_etl.egg-info/dependency_links.txt
tezos_etl.egg-info/entry_points.txt
tezos_etl.egg-info/requires.txt
tezos_etl.egg-info/top_level.txt
tezosetl/__init__.py
tezosetl/__main__.py
tezosetl/cli/__init__.py
tezosetl/cli/export.py
tezosetl/cli/export_partitioned.py
tezosetl/cli/get_block_range_for_date.py
tezosetl/enums/__init__.py
tezosetl/enums/operation_kinds.py
tezosetl/jobs/__init__.py
tezosetl/jobs/export_job.py
tezosetl/jobs/export_partitioned.py
tezosetl/jobs/exporters/__init__.py
tezosetl/jobs/exporters/tezos_item_exporter.py
tezosetl/mappers/__init__.py
tezosetl/mappers/balance_update_mapper.py
tezosetl/mappers/block_mapper.py
tezosetl/mappers/operation_mapper.py
tezosetl/rpc/__init__.py
tezosetl/rpc/request.py
tezosetl/rpc/tezos_rpc.py
tezosetl/service/__init__.py
tezosetl/service/tezos_block_range_service.py
tezosetl/service/tezos_block_timestamp_graph.py
tezosetl/service/tezos_service.py
tezosetl/utils/__init__.py
tezosetl/utils/cast_utils.py